{"_path":"/api/performmath","_dir":"api","_draft":false,"_partial":false,"_locale":"","_empty":false,"title":"performMath() function","description":"A function that takes in calculations and performs the necessary operations to generate appropriate tooltips.","body":{"type":"root","children":[{"type":"element","tag":"h2","props":{"id":"performmathcalculation-effects-datavalue-maxrank-options-function"},"children":[{"type":"text","value":"performMath(calculation, effects, datavalue, maxRank, options) function"}]},{"type":"element","tag":"p","props":{},"children":[{"type":"text","value":"A function that takes in calculations and performs the necessary operations to generate appropriate tooltips."}]},{"type":"element","tag":"p","props":{},"children":[{"type":"element","tag":"strong","props":{},"children":[{"type":"text","value":"Signature:"}]}]},{"type":"element","tag":"code","props":{"code":"export declare function performMath(calculation: {\n    [key: string]: any;\n    __type: string;\n}, effects: {\n    value: number[];\n}[], datavalue: {\n    [name: string]: number[];\n}, maxRank: number, options: {\n    percent: boolean;\n}): string;\n","language":"ts","meta":null},"children":[{"type":"element","tag":"pre","props":{},"children":[{"type":"element","tag":"code","props":{"__ignoreMap":""},"children":[{"type":"element","tag":"span","props":{"class":"line"},"children":[{"type":"element","tag":"span","props":{"class":"ct-d83b70"},"children":[{"type":"text","value":"export"}]},{"type":"element","tag":"span","props":{"class":"ct-9fd636"},"children":[{"type":"text","value":" "}]},{"type":"element","tag":"span","props":{"class":"ct-d83b70"},"children":[{"type":"text","value":"declare"}]},{"type":"element","tag":"span","props":{"class":"ct-9fd636"},"children":[{"type":"text","value":" "}]},{"type":"element","tag":"span","props":{"class":"ct-d83b70"},"children":[{"type":"text","value":"function"}]},{"type":"element","tag":"span","props":{"class":"ct-9fd636"},"children":[{"type":"text","value":" "}]},{"type":"element","tag":"span","props":{"class":"ct-3ab272"},"children":[{"type":"text","value":"performMath"}]},{"type":"element","tag":"span","props":{"class":"ct-9fd636"},"children":[{"type":"text","value":"("}]},{"type":"element","tag":"span","props":{"class":"ct-c457c2"},"children":[{"type":"text","value":"calculation"}]},{"type":"element","tag":"span","props":{"class":"ct-d83b70"},"children":[{"type":"text","value":":"}]},{"type":"element","tag":"span","props":{"class":"ct-9fd636"},"children":[{"type":"text","value":" {"}]}]},{"type":"element","tag":"span","props":{"class":"line"},"children":[{"type":"element","tag":"span","props":{"class":"ct-9fd636"},"children":[{"type":"text","value":"    ["}]},{"type":"element","tag":"span","props":{"class":"ct-c457c2"},"children":[{"type":"text","value":"key"}]},{"type":"element","tag":"span","props":{"class":"ct-d83b70"},"children":[{"type":"text","value":":"}]},{"type":"element","tag":"span","props":{"class":"ct-9fd636"},"children":[{"type":"text","value":" "}]},{"type":"element","tag":"span","props":{"class":"ct-d1e92a"},"children":[{"type":"text","value":"string"}]},{"type":"element","tag":"span","props":{"class":"ct-9fd636"},"children":[{"type":"text","value":"]"}]},{"type":"element","tag":"span","props":{"class":"ct-d83b70"},"children":[{"type":"text","value":":"}]},{"type":"element","tag":"span","props":{"class":"ct-9fd636"},"children":[{"type":"text","value":" "}]},{"type":"element","tag":"span","props":{"class":"ct-d1e92a"},"children":[{"type":"text","value":"any"}]},{"type":"element","tag":"span","props":{"class":"ct-9fd636"},"children":[{"type":"text","value":";"}]}]},{"type":"element","tag":"span","props":{"class":"line"},"children":[{"type":"element","tag":"span","props":{"class":"ct-9fd636"},"children":[{"type":"text","value":"    "}]},{"type":"element","tag":"span","props":{"class":"ct-c457c2"},"children":[{"type":"text","value":"__type"}]},{"type":"element","tag":"span","props":{"class":"ct-d83b70"},"children":[{"type":"text","value":":"}]},{"type":"element","tag":"span","props":{"class":"ct-9fd636"},"children":[{"type":"text","value":" "}]},{"type":"element","tag":"span","props":{"class":"ct-d1e92a"},"children":[{"type":"text","value":"string"}]},{"type":"element","tag":"span","props":{"class":"ct-9fd636"},"children":[{"type":"text","value":";"}]}]},{"type":"element","tag":"span","props":{"class":"line"},"children":[{"type":"element","tag":"span","props":{"class":"ct-9fd636"},"children":[{"type":"text","value":"}, "}]},{"type":"element","tag":"span","props":{"class":"ct-c457c2"},"children":[{"type":"text","value":"effects"}]},{"type":"element","tag":"span","props":{"class":"ct-d83b70"},"children":[{"type":"text","value":":"}]},{"type":"element","tag":"span","props":{"class":"ct-9fd636"},"children":[{"type":"text","value":" {"}]}]},{"type":"element","tag":"span","props":{"class":"line"},"children":[{"type":"element","tag":"span","props":{"class":"ct-9fd636"},"children":[{"type":"text","value":"    "}]},{"type":"element","tag":"span","props":{"class":"ct-c457c2"},"children":[{"type":"text","value":"value"}]},{"type":"element","tag":"span","props":{"class":"ct-d83b70"},"children":[{"type":"text","value":":"}]},{"type":"element","tag":"span","props":{"class":"ct-9fd636"},"children":[{"type":"text","value":" "}]},{"type":"element","tag":"span","props":{"class":"ct-d1e92a"},"children":[{"type":"text","value":"number"}]},{"type":"element","tag":"span","props":{"class":"ct-9fd636"},"children":[{"type":"text","value":"[];"}]}]},{"type":"element","tag":"span","props":{"class":"line"},"children":[{"type":"element","tag":"span","props":{"class":"ct-9fd636"},"children":[{"type":"text","value":"}[], "}]},{"type":"element","tag":"span","props":{"class":"ct-c457c2"},"children":[{"type":"text","value":"datavalue"}]},{"type":"element","tag":"span","props":{"class":"ct-d83b70"},"children":[{"type":"text","value":":"}]},{"type":"element","tag":"span","props":{"class":"ct-9fd636"},"children":[{"type":"text","value":" {"}]}]},{"type":"element","tag":"span","props":{"class":"line"},"children":[{"type":"element","tag":"span","props":{"class":"ct-9fd636"},"children":[{"type":"text","value":"    ["}]},{"type":"element","tag":"span","props":{"class":"ct-c457c2"},"children":[{"type":"text","value":"name"}]},{"type":"element","tag":"span","props":{"class":"ct-d83b70"},"children":[{"type":"text","value":":"}]},{"type":"element","tag":"span","props":{"class":"ct-9fd636"},"children":[{"type":"text","value":" "}]},{"type":"element","tag":"span","props":{"class":"ct-d1e92a"},"children":[{"type":"text","value":"string"}]},{"type":"element","tag":"span","props":{"class":"ct-9fd636"},"children":[{"type":"text","value":"]"}]},{"type":"element","tag":"span","props":{"class":"ct-d83b70"},"children":[{"type":"text","value":":"}]},{"type":"element","tag":"span","props":{"class":"ct-9fd636"},"children":[{"type":"text","value":" "}]},{"type":"element","tag":"span","props":{"class":"ct-d1e92a"},"children":[{"type":"text","value":"number"}]},{"type":"element","tag":"span","props":{"class":"ct-9fd636"},"children":[{"type":"text","value":"[];"}]}]},{"type":"element","tag":"span","props":{"class":"line"},"children":[{"type":"element","tag":"span","props":{"class":"ct-9fd636"},"children":[{"type":"text","value":"}, "}]},{"type":"element","tag":"span","props":{"class":"ct-c457c2"},"children":[{"type":"text","value":"maxRank"}]},{"type":"element","tag":"span","props":{"class":"ct-d83b70"},"children":[{"type":"text","value":":"}]},{"type":"element","tag":"span","props":{"class":"ct-9fd636"},"children":[{"type":"text","value":" "}]},{"type":"element","tag":"span","props":{"class":"ct-d1e92a"},"children":[{"type":"text","value":"number"}]},{"type":"element","tag":"span","props":{"class":"ct-9fd636"},"children":[{"type":"text","value":", "}]},{"type":"element","tag":"span","props":{"class":"ct-c457c2"},"children":[{"type":"text","value":"options"}]},{"type":"element","tag":"span","props":{"class":"ct-d83b70"},"children":[{"type":"text","value":":"}]},{"type":"element","tag":"span","props":{"class":"ct-9fd636"},"children":[{"type":"text","value":" {"}]}]},{"type":"element","tag":"span","props":{"class":"line"},"children":[{"type":"element","tag":"span","props":{"class":"ct-9fd636"},"children":[{"type":"text","value":"    "}]},{"type":"element","tag":"span","props":{"class":"ct-c457c2"},"children":[{"type":"text","value":"percent"}]},{"type":"element","tag":"span","props":{"class":"ct-d83b70"},"children":[{"type":"text","value":":"}]},{"type":"element","tag":"span","props":{"class":"ct-9fd636"},"children":[{"type":"text","value":" "}]},{"type":"element","tag":"span","props":{"class":"ct-d1e92a"},"children":[{"type":"text","value":"boolean"}]},{"type":"element","tag":"span","props":{"class":"ct-9fd636"},"children":[{"type":"text","value":";"}]}]},{"type":"element","tag":"span","props":{"class":"line"},"children":[{"type":"element","tag":"span","props":{"class":"ct-9fd636"},"children":[{"type":"text","value":"})"}]},{"type":"element","tag":"span","props":{"class":"ct-d83b70"},"children":[{"type":"text","value":":"}]},{"type":"element","tag":"span","props":{"class":"ct-9fd636"},"children":[{"type":"text","value":" "}]},{"type":"element","tag":"span","props":{"class":"ct-d1e92a"},"children":[{"type":"text","value":"string"}]},{"type":"element","tag":"span","props":{"class":"ct-9fd636"},"children":[{"type":"text","value":";"}]}]}]}]}]},{"type":"element","tag":"h3","props":{"id":"parameters"},"children":[{"type":"text","value":"Parameters"}]},{"type":"element","tag":"table","props":{},"children":[{"type":"element","tag":"thead","props":{},"children":[{"type":"element","tag":"tr","props":{},"children":[{"type":"element","tag":"th","props":{"align":null},"children":[{"type":"text","value":"Parameter"}]},{"type":"element","tag":"th","props":{"align":null},"children":[{"type":"text","value":"Type"}]},{"type":"element","tag":"th","props":{"align":null},"children":[{"type":"text","value":"Description"}]}]}]},{"type":"element","tag":"tbody","props":{},"children":[{"type":"element","tag":"tr","props":{},"children":[{"type":"element","tag":"td","props":{"align":null},"children":[{"type":"text","value":"calculation"}]},{"type":"element","tag":"td","props":{"align":null},"children":[{"type":"text","value":"{     "},{"type":"element","tag":"span","props":{},"children":[{"type":"text","value":"key: string"}]},{"type":"text","value":": any;     __type: string; }"}]},{"type":"element","tag":"td","props":{"align":null},"children":[{"type":"text","value":"The calculations."}]}]},{"type":"element","tag":"tr","props":{},"children":[{"type":"element","tag":"td","props":{"align":null},"children":[{"type":"text","value":"effects"}]},{"type":"element","tag":"td","props":{"align":null},"children":[{"type":"text","value":"{     value: number"},{"type":"element","tag":"span","props":{},"children":[]},{"type":"text","value":"; }"},{"type":"element","tag":"span","props":{},"children":[]}]},{"type":"element","tag":"td","props":{"align":null},"children":[{"type":"text","value":"The effect values."}]}]},{"type":"element","tag":"tr","props":{},"children":[{"type":"element","tag":"td","props":{"align":null},"children":[{"type":"text","value":"datavalue"}]},{"type":"element","tag":"td","props":{"align":null},"children":[{"type":"text","value":"{     "},{"type":"element","tag":"span","props":{},"children":[{"type":"text","value":"name: string"}]},{"type":"text","value":": number"},{"type":"element","tag":"span","props":{},"children":[]},{"type":"text","value":"; }"}]},{"type":"element","tag":"td","props":{"align":null},"children":[{"type":"text","value":"The named data values."}]}]},{"type":"element","tag":"tr","props":{},"children":[{"type":"element","tag":"td","props":{"align":null},"children":[{"type":"text","value":"maxRank"}]},{"type":"element","tag":"td","props":{"align":null},"children":[{"type":"element","tag":"a","props":{"href":"https://developer.mozilla.org/en-US/docs/Web/JavaScript/Reference/Global_Objects/Number","rel":["nofollow"]},"children":[{"type":"text","value":"Number"}]}]},{"type":"element","tag":"td","props":{"align":null},"children":[{"type":"text","value":"The max applicable spell rank."}]}]},{"type":"element","tag":"tr","props":{},"children":[{"type":"element","tag":"td","props":{"align":null},"children":[{"type":"text","value":"options"}]},{"type":"element","tag":"td","props":{"align":null},"children":[{"type":"text","value":"{     percent: boolean; }"}]},{"type":"element","tag":"td","props":{"align":null},"children":[{"type":"text","value":"Additional spell math options."}]}]}]}]},{"type":"element","tag":"p","props":{},"children":[{"type":"element","tag":"strong","props":{},"children":[{"type":"text","value":"Return type :"}]},{"type":"text","value":" "},{"type":"element","tag":"a","props":{"href":"https://developer.mozilla.org/en-US/docs/Web/JavaScript/Reference/Global_Objects/String","rel":["nofollow"]},"children":[{"type":"text","value":"String"}]}]},{"type":"element","tag":"hr","props":{},"children":[]},{"type":"element","tag":"style","children":[{"type":"text","value":".ct-d1e92a{color:#0550AE}\n.ct-c457c2{color:#953800}\n.ct-3ab272{color:#8250DF}\n.ct-9fd636{color:#24292F}\n.ct-d83b70{color:#CF222E}\n.dark .ct-d83b70{color:#FF7B72}\n.dark .ct-9fd636{color:#C9D1D9}\n.dark .ct-3ab272{color:#D2A8FF}\n.dark .ct-c457c2{color:#FFA657}\n.dark .ct-d1e92a{color:#79C0FF}"}]}],"toc":{"title":"","searchDepth":2,"depth":2,"links":[{"id":"performmathcalculation-effects-datavalue-maxrank-options-function","depth":2,"text":"performMath(calculation, effects, datavalue, maxRank, options) function","children":[{"id":"parameters","depth":3,"text":"Parameters"}]}]}},"_type":"markdown","_id":"content:api:performMath.md","_source":"content","_file":"api/performMath.md","_extension":"md"}