{"_path":"/api/lolstatusmethods","_dir":"api","_draft":false,"_partial":false,"_locale":"","_empty":false,"title":"LolStatusMethods","description":"The Lol Status API method names.","body":{"type":"root","children":[{"type":"element","tag":"h2","props":{"id":"lolstatusmethods-type"},"children":[{"type":"text","value":"LolStatusMethods type"}]},{"type":"element","tag":"p","props":{},"children":[{"type":"text","value":"The Lol Status API method names."}]},{"type":"element","tag":"p","props":{},"children":[{"type":"element","tag":"strong","props":{},"children":[{"type":"text","value":"Signature:"}]}]},{"type":"element","tag":"code","props":{"code":"export type LolStatusMethods = (typeof methods)['LOL_STATUS'][number];\n","language":"ts","meta":null},"children":[{"type":"element","tag":"pre","props":{},"children":[{"type":"element","tag":"code","props":{"__ignoreMap":""},"children":[{"type":"element","tag":"span","props":{"class":"line"},"children":[{"type":"element","tag":"span","props":{"class":"ct-9f8275"},"children":[{"type":"text","value":"export"}]},{"type":"element","tag":"span","props":{"class":"ct-cb025c"},"children":[{"type":"text","value":" "}]},{"type":"element","tag":"span","props":{"class":"ct-9f8275"},"children":[{"type":"text","value":"type"}]},{"type":"element","tag":"span","props":{"class":"ct-cb025c"},"children":[{"type":"text","value":" "}]},{"type":"element","tag":"span","props":{"class":"ct-891823"},"children":[{"type":"text","value":"LolStatusMethods"}]},{"type":"element","tag":"span","props":{"class":"ct-cb025c"},"children":[{"type":"text","value":" "}]},{"type":"element","tag":"span","props":{"class":"ct-9f8275"},"children":[{"type":"text","value":"="}]},{"type":"element","tag":"span","props":{"class":"ct-cb025c"},"children":[{"type":"text","value":" ("}]},{"type":"element","tag":"span","props":{"class":"ct-9f8275"},"children":[{"type":"text","value":"typeof"}]},{"type":"element","tag":"span","props":{"class":"ct-cb025c"},"children":[{"type":"text","value":" methods)["}]},{"type":"element","tag":"span","props":{"class":"ct-2cbe3c"},"children":[{"type":"text","value":"'LOL_STATUS'"}]},{"type":"element","tag":"span","props":{"class":"ct-cb025c"},"children":[{"type":"text","value":"]["}]},{"type":"element","tag":"span","props":{"class":"ct-57b8a7"},"children":[{"type":"text","value":"number"}]},{"type":"element","tag":"span","props":{"class":"ct-cb025c"},"children":[{"type":"text","value":"];"}]}]}]}]}]},{"type":"element","tag":"p","props":{},"children":[{"type":"element","tag":"strong","props":{},"children":[{"type":"text","value":"References:"}]},{"type":"text","value":" "},{"type":"element","tag":"a","props":{"href":"/api/methods"},"children":[{"type":"text","value":"methods"}]}]},{"type":"element","tag":"style","children":[{"type":"text","value":".ct-57b8a7{color:#0550AE}\n.ct-2cbe3c{color:#0A3069}\n.ct-891823{color:#953800}\n.ct-cb025c{color:#24292F}\n.ct-9f8275{color:#CF222E}\n.dark .ct-9f8275{color:#FF7B72}\n.dark .ct-cb025c{color:#C9D1D9}\n.dark .ct-891823{color:#FFA657}\n.dark .ct-2cbe3c{color:#A5D6FF}\n.dark .ct-57b8a7{color:#79C0FF}"}]}],"toc":{"title":"","searchDepth":2,"depth":2,"links":[{"id":"lolstatusmethods-type","depth":2,"text":"LolStatusMethods type"}]}},"_type":"markdown","_id":"content:api:LolStatusMethods.md","_source":"content","_file":"api/LolStatusMethods.md","_extension":"md"}