{"_path":"/api/variables/rawstatperks","_dir":"variables","_draft":false,"_partial":false,"_locale":"","_empty":false,"title":"rawStatPerks","description":"The available stat perks.","body":{"type":"root","children":[{"type":"element","tag":"h2","props":{"id":"rawstatperks-variable"},"children":[{"type":"text","value":"rawStatPerks variable"}]},{"type":"element","tag":"p","props":{},"children":[{"type":"text","value":"The available stat perks."}]},{"type":"element","tag":"p","props":{},"children":[{"type":"element","tag":"strong","props":{},"children":[{"type":"text","value":"Signature:"}]}]},{"type":"element","tag":"code","props":{"code":"rawStatPerks: {\n    [key: number]: StatPerk;\n}\n","language":"ts","meta":null},"children":[{"type":"element","tag":"pre","props":{},"children":[{"type":"element","tag":"code","props":{"__ignoreMap":""},"children":[{"type":"element","tag":"span","props":{"class":"line"},"children":[{"type":"element","tag":"span","props":{"class":"ct-ded7d3"},"children":[{"type":"text","value":"rawStatPerks"}]},{"type":"element","tag":"span","props":{"class":"ct-60f9b1"},"children":[{"type":"text","value":": {"}]}]},{"type":"element","tag":"span","props":{"class":"line"},"children":[{"type":"element","tag":"span","props":{"class":"ct-60f9b1"},"children":[{"type":"text","value":"    [key: number]: StatPerk;"}]}]},{"type":"element","tag":"span","props":{"class":"line"},"children":[{"type":"element","tag":"span","props":{"class":"ct-60f9b1"},"children":[{"type":"text","value":"}"}]}]}]}]}]},{"type":"element","tag":"p","props":{},"children":[{"type":"element","tag":"strong","props":{},"children":[{"type":"text","value":"References:"}]},{"type":"text","value":" "},{"type":"element","tag":"a","props":{"href":"/api/interfaces/statperk"},"children":[{"type":"text","value":"StatPerk"}]}]},{"type":"element","tag":"style","children":[{"type":"text","value":".ct-60f9b1{color:#24292F}\n.ct-ded7d3{color:#953800}\n.dark .ct-ded7d3{color:#FFA657}\n.dark .ct-60f9b1{color:#C9D1D9}"}]}],"toc":{"title":"","searchDepth":2,"depth":2,"links":[{"id":"rawstatperks-variable","depth":2,"text":"rawStatPerks variable"}]}},"_type":"markdown","_id":"content:2.api:5.variables:rawStatPerks.md","_source":"content","_file":"2.api/5.variables/rawStatPerks.md","_extension":"md"}