[{"_path":"/api/interfaces/challengerankdata","_dir":"interfaces","_draft":false,"_partial":false,"_locale":"","_empty":false,"title":"ChallengeRankData","description":"The raw data regarding a player's placement in a challenge ladder.","_type":"markdown","_id":"content:2.api:2.interfaces:ChallengeRankData.md","_source":"content","_file":"2.api/2.interfaces/ChallengeRankData.md","_extension":"md"},{"_path":"/api/interfaces/championdata","_dir":"interfaces","_draft":false,"_partial":false,"_locale":"","_empty":false,"title":"ChampionData","description":"A representation of the champion data returned by Data Dragon.","_type":"markdown","_id":"content:2.api:2.interfaces:ChampionData.md","_source":"content","_file":"2.api/2.interfaces/ChampionData.md","_extension":"md"}]